unirule/__init__.py
unirule/__main__.py
unirule/exception.py
unirule/util.py
unirule/exporter/__init__.py
unirule/exporter/dlc.py
unirule/exporter/metadomain.py
unirule/exporter/metaipcidr.py
unirule/exporter/singbox.py
unirule/importer/__init__.py
unirule/importer/adguarddns.py
unirule/importer/dlc.py
unirule/importer/metadomain.py
unirule/importer/metaipcidr.py
unirule/importer/singbox.py
unirule-0.3.1.dist-info/METADATA
unirule-0.3.1.dist-info/WHEEL
unirule-0.3.1.dist-info/entry_points.txt
unirule-0.3.1.dist-info/licenses/LICENSE.txt
unirule-0.3.1.dist-info/RECORD
