Metadata-Version: 2.4
Name: unirule
Version: 0.3.1
Summary: Rule converter for proxy platforms.
Project-URL: Homepage, https://github.com/TargetLocked/unirule
Project-URL: Repository, https://github.com/TargetLocked/unirule
Author-email: TargetLocked <32962687+TargetLocked@users.noreply.github.com>
License: GPL-3.0-or-later
License-File: LICENSE.txt
Classifier: Development Status :: 3 - Alpha
Classifier: Intended Audience :: Developers
Classifier: License :: OSI Approved :: GNU General Public License v3 or later (GPLv3+)
Requires-Python: >=3.12.10
Requires-Dist: pyyaml>=6.0.2
